CHANGELOG.txt
LICENSE
MANIFEST.in
README.rst
setup.py
src/ua2/__init__.py
src/ua2.table3.egg-info/PKG-INFO
src/ua2.table3.egg-info/SOURCES.txt
src/ua2.table3.egg-info/dependency_links.txt
src/ua2.table3.egg-info/eager_resources.txt
src/ua2.table3.egg-info/namespace_packages.txt
src/ua2.table3.egg-info/not-zip-safe
src/ua2.table3.egg-info/requires.txt
src/ua2.table3.egg-info/top_level.txt
src/ua2/table3/__init__.py
src/ua2/table3/bound.py
src/ua2/table3/column.py
src/ua2/table3/data.py
src/ua2/table3/plugin.py
src/ua2/table3/render.py
src/ua2/table3/request.py
src/ua2/table3/settings.py
src/ua2/table3/table.py
src/ua2/table3/utils.py
src/ua2/table3/plugins/__init__.py
src/ua2/table3/plugins/actions.py
src/ua2/table3/plugins/filters.py
src/ua2/table3/plugins/output.py
src/ua2/table3/plugins/paginator.py
src/ua2/table3/plugins/quicksearch.py
src/ua2/table3/plugins/sortable.py
src/ua2/table3/templates/ua2/table3/category.html
src/ua2/table3/templates/ua2/table3/dropdown.html
src/ua2/table3/templates/ua2/table3/header_checkbox.html
src/ua2/table3/templates/ua2/table3/header_column.html
src/ua2/table3/templates/ua2/table3/main.html
src/ua2/table3/templates/ua2/table3/paginator.html
src/ua2/table3/templates/ua2/table3/post_action.html
src/ua2/table3/templates/ua2/table3/quicksearch.html
src/ua2/table3/templatetags/__init__.py
src/ua2/table3/templatetags/table3.py