Metadata-Version: 1.1
Name: ua2.table3
Version: 0.6.0
Summary: Alternative package for rendering tables
Home-page: https://bitbucket.org/vic_in_kh/ua2.table3
Author: Viacheslav Vic Bukhantsov
Author-email: vic@ua2crm.com
License: BSD License
Platform: OS Independent
Classifier: Development Status :: 3 - Alpha
Classifier: Intended Audience :: Developers
Classifier: Framework :: Django
Classifier: License :: OSI Approved :: BSD License
Classifier: Operating System :: OS Independent
Classifier: Programming Language :: Python
Classifier: Programming Language :: Python :: 2
Classifier: Programming Language :: Python :: 3
Classifier: Topic :: Internet :: WWW/HTTP :: Dynamic Content
Classifier: Topic :: Software Development
Classifier: Topic :: Software Development :: Libraries
